examples/__init__.py
examples/generic_example.py
examples/multiple_depot_multiple_driver.py
examples/multiple_depot_multiple_driver_time_window.py
examples/multiple_depot_multiple_driver_with_24_stops_time_window.py
examples/single_depot_multiple_driver.py
examples/single_depot_multiple_driver_time_window.py
examples/single_driver_round_trip.py
examples/single_driver_round_trip_reoptimization.py
examples/single_driver_route_10_stops.py
route4me/__init__.py
route4me/activity_feed.py
route4me/address.py
route4me/address_book.py
route4me/api.py
route4me/api_endpoints.py
route4me/avoidance_zones.py
route4me/base.py
route4me/constants.py
route4me/exceptions.py
route4me/file_uploading.py
route4me/gps.py
route4me/members.py
route4me/optimization.py
route4me/orders.py
route4me/rapid_address.py
route4me/route.py
route4me/territory.py
route4me/utils.py
route4me/vehicles.py
route4me/version.py
tests/__init__.py
tests/base.py
tests/test_addresses.py
tests/test_gps.py
tests/test_optimizations.py
tests/test_routes.py
tests/test_territory.py
tests/test_utils.py
tests/test_vehicles.py
route4me-0.0.7.1.dist-info/LICENSE.md
route4me-0.0.7.1.dist-info/METADATA
route4me-0.0.7.1.dist-info/WHEEL
route4me-0.0.7.1.dist-info/top_level.txt
route4me-0.0.7.1.dist-info/zip-safe
route4me-0.0.7.1.dist-info/RECORD
