Metadata-Version: 2.1
Name: route4me
Version: 0.0.7.1
Summary: Route4Me Python SDK
Home-page: https://github.com/route4me/route4me-python-sdk
Author: Route4Me Python Team (SDK)
Author-email: juan@route4me.com
License: ISC
Keywords: rout4me,python,sdk,api
Platform: any
Classifier: Environment :: Other Environment
Classifier: License :: OSI Approved :: ISC License (ISCL)
Classifier: Operating System :: OS Independent
Classifier: Programming Language :: Python
Classifier: Programming Language :: Python :: 3.6
Classifier: Programming Language :: Python :: 3.7
Classifier: Programming Language :: Python :: 3.8
Classifier: Programming Language :: Python :: Implementation
Classifier: Programming Language :: Python :: Implementation :: CPython
Classifier: Programming Language :: Python :: Implementation :: PyPy
Classifier: Topic :: Software Development :: Libraries :: Python Modules
Requires-Dist: six
Requires-Dist: requests
